privacy_idea_struct/__init__.py
privacy_idea_struct/main.py
privacy_idea_struct/prompts.py
privacy_idea_struct-2025.12.21083159.dist-info/METADATA
privacy_idea_struct-2025.12.21083159.dist-info/WHEEL
privacy_idea_struct-2025.12.21083159.dist-info/top_level.txt
privacy_idea_struct-2025.12.21083159.dist-info/RECORD
