Metadata-Version: 2.4
Name: privacy-idea-struct
Version: 2025.12.21083159
Summary: A new package that enables users to provide simple text inputs about innovative, privacy-focused services—such as a phone company that doesn't collect personal data—and receive structured summaries or
Author-email: privacy-idea-struct <hi@eugene.plus>
License: MIT
Project-URL: Homepage, https://github.com/chigwell/privacy-idea-struct
Requires-Python: >=3.9
Requires-Dist: langchain-llm7>=0.0.0
Requires-Dist: llmatch-messages>=0.0.0
Requires-Dist: langchain-core>=0.3.0
